.travis.yml
.zopeskel
CHANGES.txt
CONTRIBUTORS.txt
Makefile
README.txt
setup.py
version.txt
docs/LICENSE.GPL
docs/LICENSE.txt
docs/Makefile
docs/source/conf.py
docs/source/index.rst
docs/source/_static/.empty
docs/source/_templates/indexsidebar.html
docs/source/_themes/bootstrap.zip
example.dotdot.package/.travis.yml
example.dotdot.package/.zopeskel
example.dotdot.package/CHANGES.txt
example.dotdot.package/CONTRIBUTORS.txt
example.dotdot.package/Makefile
example.dotdot.package/README.txt
example.dotdot.package/setup.py
example.dotdot.package/docs/LICENSE.GPL
example.dotdot.package/docs/LICENSE.txt
example.dotdot.package/docs/Makefile
example.dotdot.package/docs/source/conf.py
example.dotdot.package/docs/source/index.rst
example.dotdot.package/docs/source/_static/.empty
example.dotdot.package/docs/source/_templates/indexsidebar.html
example.dotdot.package/docs/source/_themes/bootstrap.zip
example.dotdot.package/example/__init__.py
example.dotdot.package/example.dotdot.package.egg-info/PKG-INFO
example.dotdot.package/example.dotdot.package.egg-info/SOURCES.txt
example.dotdot.package/example.dotdot.package.egg-info/dependency_links.txt
example.dotdot.package/example.dotdot.package.egg-info/entry_points.txt
example.dotdot.package/example.dotdot.package.egg-info/namespace_packages.txt
example.dotdot.package/example.dotdot.package.egg-info/not-zip-safe
example.dotdot.package/example.dotdot.package.egg-info/requires.txt
example.dotdot.package/example.dotdot.package.egg-info/top_level.txt
example.dotdot.package/example/dotdot/__init__.py
example.dotdot.package/example/dotdot/package/__init__.py
example.dotdot.package/example/dotdot/package/tests/__init__.py
example.dotdot.package/example/dotdot/package/tests/test_package.py
example.dotpackage/.travis.yml
example.dotpackage/.zopeskel
example.dotpackage/CHANGES.txt
example.dotpackage/CONTRIBUTORS.txt
example.dotpackage/Makefile
example.dotpackage/README.txt
example.dotpackage/setup.py
example.dotpackage/docs/LICENSE.GPL
example.dotpackage/docs/LICENSE.txt
example.dotpackage/docs/Makefile
example.dotpackage/docs/source/conf.py
example.dotpackage/docs/source/index.rst
example.dotpackage/docs/source/_static/.empty
example.dotpackage/docs/source/_templates/indexsidebar.html
example.dotpackage/docs/source/_themes/bootstrap.zip
example.dotpackage/example/__init__.py
example.dotpackage/example.dotpackage.egg-info/PKG-INFO
example.dotpackage/example.dotpackage.egg-info/SOURCES.txt
example.dotpackage/example.dotpackage.egg-info/dependency_links.txt
example.dotpackage/example.dotpackage.egg-info/entry_points.txt
example.dotpackage/example.dotpackage.egg-info/namespace_packages.txt
example.dotpackage/example.dotpackage.egg-info/not-zip-safe
example.dotpackage/example.dotpackage.egg-info/requires.txt
example.dotpackage/example.dotpackage.egg-info/top_level.txt
example.dotpackage/example/dotpackage/__init__.py
example.dotpackage/example/dotpackage/tests/__init__.py
example.dotpackage/example/dotpackage/tests/test_dotpackage.py
examplepackage/.travis.yml
examplepackage/examplepackage.egg-info/PKG-INFO
examplepackage/examplepackage.egg-info/SOURCES.txt
examplepackage/examplepackage.egg-info/dependency_links.txt
examplepackage/examplepackage.egg-info/entry_points.txt
examplepackage/examplepackage.egg-info/not-zip-safe
examplepackage/examplepackage.egg-info/requires.txt
examplepackage/examplepackage.egg-info/top_level.txt
tooth.paste.egg-info/PKG-INFO
tooth.paste.egg-info/SOURCES.txt
tooth.paste.egg-info/dependency_links.txt
tooth.paste.egg-info/entry_points.txt
tooth.paste.egg-info/namespace_packages.txt
tooth.paste.egg-info/not-zip-safe
tooth.paste.egg-info/requires.txt
tooth.paste.egg-info/top_level.txt
