Metadata-Version: 1.1
Name: tooth.paste
Version: 2.0
Summary: Create shiny new Python packages with Sphinx documentation, unit tests and tools to keep your code clean
Home-page: https://github.com/maikroeder/tooth.paste.git
Author: Maik Roder
Author-email: maikroeder@gmail.com
License: gpl
Keywords: Tooth,paste
Platform: UNKNOWN
Classifier: Programming Language :: Python
